vtda/__init__.py
vtda/analysis/__init__.py
vtda/analysis/base.py
vtda/analysis/batch_calculate.py
vtda/analysis/noise.py
vtda/analysis/sperling.py
vtda/analysis/untitled1.py
vtda/analysis/vehicle_dynamics.py
vtda/analysis/vibration.py
vtda/demo/__init__.py
vtda/demo/algo.py
vtda/demo/demo_dxp_to_dasp.py
vtda/demo/demo_sperling.py
vtda/demo/demo_vibration_noise.py
vtda/read_data/__init__.py
vtda/read_data/read_dasc.py
vtda/read_data/read_dasp.py
vtda/read_data/read_dxd.py
vtda/test/__init__.py
vtda/test/find_start_and_end.py
vtda/test/test.py
vtda/util/__init__.py
vtda/util/util.py
vtda-1.5.3.dist-info/METADATA
vtda-1.5.3.dist-info/WHEEL
vtda-1.5.3.dist-info/top_level.txt
vtda-1.5.3.dist-info/RECORD
